st/__init__.py
student_tools-0.3.3.dist-info/licenses/LICENSE
student_tools-0.3.3.dist-info/licenses/LICENSE.md
student_tools-0.3.3.dist-info/METADATA
student_tools-0.3.3.dist-info/WHEEL
student_tools-0.3.3.dist-info/top_level.txt
student_tools-0.3.3.dist-info/RECORD
