Metadata-Version: 2.4
Name: student_tools
Version: 0.3.3
Summary: [Python 3.12 Recommended] A collection of English, Math, and Utility tools, made for students.
Author: Error Dev
Author-email: 3rr0r.d3v@gmail.com
License: Proprietary
Classifier: Programming Language :: Python
Classifier: Environment :: Console
Classifier: Framework :: IDLE
Classifier: Natural Language :: English
Requires-Python: >=3.6,<3.13
License-File: LICENSE.md
License-File: LICENSE
Requires-Dist: sympy
Requires-Dist: pyfiglet
Requires-Dist: requests
Requires-Dist: packaging
Dynamic: author
Dynamic: author-email
Dynamic: classifier
Dynamic: description
Dynamic: description-content-type
Dynamic: license
Dynamic: license-file
Dynamic: requires-dist
Dynamic: requires-python
Dynamic: summary
